{"SQR": {"losses": {"573_cpu_act": []}, "coverage": {"573_cpu_act": []}, "complexity": {"573_cpu_act": []}, "time_all": {"573_cpu_act": []}, "time_fit": {"573_cpu_act": []}, "sizes": {"573_cpu_act": []}, "tau": 0.9}, "LightGBM": {"losses": {"573_cpu_act": []}, "coverage": {"573_cpu_act": []}, "time_all": {"573_cpu_act": []}, "time_fit": {"573_cpu_act": []}, "sizes": {"573_cpu_act": []}, "tau": 0.9}, "DecisionTree": {"losses": {"573_cpu_act": []}, "coverage": {"573_cpu_act": []}, "complexity": {"573_cpu_act": []}, "time_all": {"573_cpu_act": []}, "time_fit": {"573_cpu_act": []}, "sizes": {"573_cpu_act": []}, "tau": 0.9}, "LinearQuantile": {"losses": {"573_cpu_act": []}, "coverage": {"573_cpu_act": []}, "complexity": {"573_cpu_act": []}, "time_all": {"573_cpu_act": []}, "time_fit": {"573_cpu_act": []}, "sizes": {"573_cpu_act": []}, "tau": 0.9}}